huaweicloudsdkbss/__init__.py
huaweicloudsdkbss/v2/__init__.py
huaweicloudsdkbss/v2/bss_async_client.py
huaweicloudsdkbss/v2/bss_client.py
huaweicloudsdkbss/v2/model/__init__.py
huaweicloudsdkbss/v2/model/account_balance_v2.py
huaweicloudsdkbss/v2/model/account_balance_v3.py
huaweicloudsdkbss/v2/model/account_change_record.py
huaweicloudsdkbss/v2/model/account_manager.py
huaweicloudsdkbss/v2/model/adjust_account_req.py
huaweicloudsdkbss/v2/model/adjust_coupon_quotas_req.py
huaweicloudsdkbss/v2/model/adjust_record_v3.py
huaweicloudsdkbss/v2/model/adjust_to_indirect_partner_req.py
huaweicloudsdkbss/v2/model/agent_pay_info_v2.py
huaweicloudsdkbss/v2/model/amount_infomation_v2.py
huaweicloudsdkbss/v2/model/apply_enterprise_realname_auths_req.py
huaweicloudsdkbss/v2/model/apply_individual_realname_auths_req.py
huaweicloudsdkbss/v2/model/auto_renewal_resources_req.py
huaweicloudsdkbss/v2/model/auto_renewal_resources_request.py
huaweicloudsdkbss/v2/model/auto_renewal_resources_response.py
huaweicloudsdkbss/v2/model/avail_retrieve_coupons.py
huaweicloudsdkbss/v2/model/avail_transfer_coupon.py
huaweicloudsdkbss/v2/model/az_code_info.py
huaweicloudsdkbss/v2/model/balance_type_deduct_sum_v2.py
huaweicloudsdkbss/v2/model/bank_card_info_v2.py
huaweicloudsdkbss/v2/model/bill_sum_info_v2.py
huaweicloudsdkbss/v2/model/bill_sum_record_info_v2.py
huaweicloudsdkbss/v2/model/cancel_auto_renewal_resources_request.py
huaweicloudsdkbss/v2/model/cancel_auto_renewal_resources_response.py
huaweicloudsdkbss/v2/model/cancel_customer_order_req.py
huaweicloudsdkbss/v2/model/cancel_customer_order_request.py
huaweicloudsdkbss/v2/model/cancel_customer_order_response.py
huaweicloudsdkbss/v2/model/cancel_resources_subscription_request.py
huaweicloudsdkbss/v2/model/cancel_resources_subscription_response.py
huaweicloudsdkbss/v2/model/change_enterprise_realname_authentication_request.py
huaweicloudsdkbss/v2/model/change_enterprise_realname_authentication_response.py
huaweicloudsdkbss-3.1.184.dist-info/METADATA
huaweicloudsdkbss-3.1.184.dist-info/WHEEL
huaweicloudsdkbss-3.1.184.dist-info/licenses/LICENSE
huaweicloudsdkbss-3.1.184.dist-info/RECORD
